ttkthemes-2.1.0.data/purelib/ttkthemes/__init__.py
ttkthemes-2.1.0.data/purelib/ttkthemes/_imgops.py
ttkthemes-2.1.0.data/purelib/ttkthemes/_tkinter.py
ttkthemes-2.1.0.data/purelib/ttkthemes/_utils.py
ttkthemes-2.1.0.data/purelib/ttkthemes/_widget.py
ttkthemes-2.1.0.data/purelib/ttkthemes/themed_style.py
ttkthemes-2.1.0.data/purelib/ttkthemes/themed_tk.py
ttkthemes-2.1.0.data/purelib/ttkthemes/advanced/pkgIndex.tcl
ttkthemes-2.1.0.data/purelib/ttkthemes/advanced/pkgIndex_package.tcl
ttkthemes-2.1.0.data/purelib/ttkthemes/gif/pkgIndex.tcl
ttkthemes-2.1.0.data/purelib/ttkthemes/gif/arc/LICENSE
ttkthemes-2.1.0.data/purelib/ttkthemes/gif/arc/arc.tcl
ttkthemes-2.1.0.data/purelib/ttkthemes/gif/arc/pkgIndex.tcl
ttkthemes-2.1.0.data/purelib/ttkthemes/gif/arc/arc/arrow-down-insens.gif
ttkthemes-2.1.0.data/purelib/ttkthemes/gif/arc/arc/arrow-down-prelight.gif
ttkthemes-2.1.0.data/purelib/ttkthemes/gif/arc/arc/arrow-down-small-insens.gif
ttkthemes-2.1.0.data/purelib/ttkthemes/gif/arc/arc/arrow-down-small-prelight.gif
ttkthemes-2.1.0.data/purelib/ttkthemes/gif/arc/arc/arrow-down-small.gif
ttkthemes-2.1.0.data/purelib/ttkthemes/gif/arc/arc/arrow-down.gif
ttkthemes-2.1.0.data/purelib/ttkthemes/gif/arc/arc/arrow-left-insens.gif
ttkthemes-2.1.0.data/purelib/ttkthemes/gif/arc/arc/arrow-left-prelight.gif
ttkthemes-2.1.0.data/purelib/ttkthemes/gif/arc/arc/arrow-left.gif
ttkthemes-2.1.0.data/purelib/ttkthemes/gif/arc/arc/arrow-right-insens.gif
ttkthemes-2.1.0.data/purelib/ttkthemes/gif/arc/arc/arrow-right-prelight.gif
ttkthemes-2.1.0.data/purelib/ttkthemes/gif/arc/arc/arrow-right.gif
ttkthemes-2.1.0.data/purelib/ttkthemes/gif/arc/arc/arrow-up-insens.gif
ttkthemes-2.1.0.data/purelib/ttkthemes/gif/arc/arc/arrow-up-prelight.gif
ttkthemes-2.1.0.data/purelib/ttkthemes/gif/arc/arc/arrow-up-small-insens.gif
ttkthemes-2.1.0.data/purelib/ttkthemes/gif/arc/arc/arrow-up-small-prelight.gif
ttkthemes-2.1.0.data/purelib/ttkthemes/gif/arc/arc/arrow-up-small.gif
ttkthemes-2.1.0.dist-info/METADATA
ttkthemes-2.1.0.dist-info/RECORD
ttkthemes-2.1.0.dist-info/WHEEL
ttkthemes-2.1.0.dist-info/top_level.txt
