Metadata-Version: 2.1
Name: ttkthemes
Version: 2.1.0
Summary: A group of themes for the ttk extensions of Tkinter with a Tkinter.Tk wrapper
Home-page: https://github.com/RedFantom/ttkthemes
Author: The ttkthemes authors
Author-email: redfantom@outlook.com
License: GPLv3
Download-URL: https://github.com/RedFantom/ttkthemes/releases
Keywords: tkinter,ttk,gui,tcl,theme
Platform: UNKNOWN
Classifier: Programming Language :: Python :: 2.7
Classifier: Programming Language :: Python :: 3.4
Classifier: Programming Language :: Python :: 3.5
Classifier: Programming Language :: Python :: 3.6
Classifier: Environment :: Win32 (MS Windows)
Classifier: Environment :: X11 Applications
Classifier: License :: OSI Approved :: GNU General Public License v3 (GPLv3)
Classifier: Topic :: Software Development :: Libraries :: Tcl Extensions
Classifier: Topic :: Software Development :: Libraries :: Python Modules
Requires-Dist: pillow
